fidelity/__init__.py
fidelity/fidelity.py
fidelity_api-0.0.16.dist-info/licenses/LICENSE
fidelity_api-0.0.16.dist-info/METADATA
fidelity_api-0.0.16.dist-info/WHEEL
fidelity_api-0.0.16.dist-info/top_level.txt
fidelity_api-0.0.16.dist-info/RECORD
