Metadata-Version: 2.4
Name: fidelity-api
Version: 0.0.16
Summary: An unofficial API for Fidelity
Home-page: https://github.com/kennyboy106/fidelity-api
Author: Kenneth Tang
License: GPL
Keywords: FIDELITY,API
License-File: LICENSE
Requires-Dist: playwright
Requires-Dist: playwright-sm
Requires-Dist: pyotp
Dynamic: author
Dynamic: description
Dynamic: description-content-type
Dynamic: home-page
Dynamic: keywords
Dynamic: license
Dynamic: license-file
Dynamic: requires-dist
Dynamic: summary
